eds_utils/__init__.py
eds_utils/__main__.py
eds_utils/eds2c.py
eds_utils/eds2dcf.py
eds_utils/eds2md.py
eds_utils/eds2rst.py
eds_utils/eds_autofix.py
eds_utils/eds_merge.py
eds_utils/eds_validate.py
eds_utils/core/__init__.py
eds_utils/core/eds.py
eds_utils/core/objects.py
eds_utils/core/file_io/__init__.py
eds_utils/core/file_io/read_eds.py
eds_utils/core/file_io/write_canopennode.py
eds_utils/core/file_io/write_eds.py
eds_utils/core/file_io/write_md.py
eds_utils/core/file_io/write_rst.py
eds_utils/eds_editor/__init__.py
eds_utils/eds_editor/app.py
eds_utils/eds_editor/eds_notebook.py
eds_utils/eds_editor/main.py
eds_utils/eds_editor/window.py
eds_utils/eds_editor/dialogs/__init__.py
eds_utils/eds_editor/dialogs/add_mapped_object_dialog.py
eds_utils/eds_editor/dialogs/add_object_dialog.py
eds_utils/eds_editor/dialogs/copy_object_dialog.py
eds_utils/eds_editor/dialogs/errors_dialog.py
eds_utils/eds_editor/dialogs/open_tmp_dialog.py
eds_utils/eds_editor/pages/__init__.py
eds_utils/eds_editor/pages/_object_grid.py
eds_utils/eds_editor/pages/device_commissioning_page.py
eds_utils/eds_editor/pages/general_info_page.py
eds_utils/eds_editor/pages/object_dictionary_page.py
eds_utils/eds_editor/pages/page.py
eds_utils/eds_editor/pages/pdo_page.py
tests/__init__.py
tests/test_eds.py
tests/test_objects.py
eds_utils-0.3.1.dist-info/LICENSE
eds_utils-0.3.1.dist-info/METADATA
eds_utils-0.3.1.dist-info/WHEEL
eds_utils-0.3.1.dist-info/entry_points.txt
eds_utils-0.3.1.dist-info/top_level.txt
eds_utils-0.3.1.dist-info/RECORD
