Metadata-Version: 2.1
Name: eds-utils
Version: 0.3.1
Summary: Utilities for editing CANopen EDS/DCF files
Home-page: https://github.com/oresat/eds-utils
Author: psas
Author-email: oresat@pdx.edu
Maintainer: psas
Maintainer-email: oresat@pdx.edu
License: GPL-3.0
Classifier: Environment :: X11 Applications :: GTK
Classifier: Intended Audience :: Developers
Classifier: License :: OSI Approved :: GNU General Public License v3 (GPLv3)
Classifier: Operating System :: OS Independent
Classifier: Programming Language :: Python :: 3
Classifier: Programming Language :: Python :: 3.7
Classifier: Programming Language :: Python :: 3.8
Classifier: Programming Language :: Python :: 3.9
Classifier: Programming Language :: Python :: 3.10
Classifier: Topic :: Software Development :: Embedded Systems
Requires-Python: >=3.7
License-File: LICENSE
Provides-Extra: ui
Requires-Dist: PyGObject ; extra == 'ui'
